{"commit_hash": "c9813ca295063e0fb182064a132ed22d7be1b655", "env_name": "virtualenv-py3.12-Cython-build-packaging", "date": 1756830287000, "params": {"machine": "gh-runner", "python": "3.12", "Cython": "", "build": "", "packaging": ""}, "python": "3.12", "requirements": {"Cython": "", "build": "", "packaging": ""}, "env_vars": {}, "result_columns": ["result", "params", "version", "started_at", "duration", "stats_ci_99_a", "stats_ci_99_b", "stats_q_25", "stats_q_75", "stats_number", "stats_repeat", "samples", "profile"], "results": {"benchmarks.time_computation": [[3.816599143000005], [], "089635b7375b19f5c790c7337625b200db3327a27d63c756ac5dbb4c1fc25b62", 1756830421221, 24.176, [2.7626], [4.7841], [3.7541], [4.0605], [1], [5]], "benchmarks.mem_list": [[496], [], "a31e7e31a99db6599fc29032ea5a3cb9782922117f13e122a69c2745a93c3d32", 1756830421216, 0.004432]}, "durations": {"<build>": 2.982753038406372}, "version": 2}